petri_net_core/__init__.py
petri_net_core/object_petrinet/__init__.py
petri_net_core/object_petrinet/opnet.py
petri_net_core/object_petrinet/opnet2pnet.py
petri_net_core/object_petrinet/opnet_schema.json
petri_net_core/object_petrinet/opnet_validator.py
petri_net_core/petrinet/__init__.py
petri_net_core/petrinet/pnet.py
petri_net_core/petrinet/pnet_schema.json
petri_net_core/petrinet/pnet_simulation_helper.py
petri_net_core/petrinet/pnet_validator.py
petri_net_core-0.3.6.dist-info/licenses/LICENSE
petri_net_core-0.3.6.dist-info/METADATA
petri_net_core-0.3.6.dist-info/WHEEL
petri_net_core-0.3.6.dist-info/top_level.txt
petri_net_core-0.3.6.dist-info/RECORD
