Metadata-Version: 2.4
Name: petri-net-core
Version: 0.3.6
Summary: Petri net simulation and analysis framework
Author: lhcnetop
License: Apache-2.0
Project-URL: Homepage, https://github.com/lhcnetop/petri_net
Project-URL: Repository, https://github.com/lhcnetop/petri_net
Project-URL: Issues, https://github.com/lhcnetop/petri_net/issues
Classifier: Development Status :: 3 - Alpha
Classifier: Intended Audience :: Science/Research
Classifier: License :: OSI Approved :: Apache Software License
Classifier: Operating System :: OS Independent
Classifier: Programming Language :: Python :: 3
Classifier: Programming Language :: Python :: 3.8
Classifier: Programming Language :: Python :: 3.9
Classifier: Programming Language :: Python :: 3.10
Classifier: Programming Language :: Python :: 3.11
Classifier: Topic :: Scientific/Engineering :: Bio-Informatics
Classifier: Topic :: Scientific/Engineering :: Mathematics
Requires-Python: >=3.8
License-File: LICENSE
Requires-Dist: jsonschema>=3.0.0
Requires-Dist: numpy>=1.20.0
Requires-Dist: polars>=0.19.0
Provides-Extra: dev
Requires-Dist: pytest>=6.0; extra == "dev"
Requires-Dist: pytest-cov>=2.0; extra == "dev"
Requires-Dist: black>=21.0; extra == "dev"
Requires-Dist: flake8>=3.8; extra == "dev"
Dynamic: license-file
